sigkerax/__init__.py
sigkerax/sigkernel.py
sigkerax/solver.py
sigkerax/static_kernels.py
sigkerax/utils.py
sigkerax-0.2.1.dist-info/LICENSE
sigkerax-0.2.1.dist-info/METADATA
sigkerax-0.2.1.dist-info/WHEEL
sigkerax-0.2.1.dist-info/RECORD
