Metadata-Version: 2.1
Name: sigkerax
Version: 0.2.1
Summary: Signature kernel computations via PDE solvers in JAX
Home-page: https://github.com/crispitagorico/sigkerax
Keywords: jax,signatures,kernels,PDE-solvers
Author: Cristopher Salvi
Author-email: crispitagorico@gmail.com
Requires-Python: >=3.8,<4.0
Classifier: Development Status :: 3 - Alpha
Classifier: Intended Audience :: Developers
Classifier: Intended Audience :: Financial and Insurance Industry
Classifier: Intended Audience :: Information Technology
Classifier: Intended Audience :: Science/Research
Classifier: License :: OSI Approved :: Apache Software License
Classifier: Natural Language :: English
Classifier: Programming Language :: Python :: 3
Classifier: Programming Language :: Python :: 3.8
Classifier: Programming Language :: Python :: 3.9
Classifier: Programming Language :: Python :: 3.10
Classifier: Programming Language :: Python :: 3.11
Classifier: Topic :: Scientific/Engineering :: Artificial Intelligence
Classifier: Topic :: Scientific/Engineering :: Information Analysis
Classifier: Topic :: Scientific/Engineering :: Mathematics
Requires-Dist: jax (>=0.4.11,<0.5.0)
Project-URL: Repository, https://github.com/crispitagorico/sigkerax
